ytmagic/__main__.py
ytmagic-1.3.4.dist-info/licenses/LICENSE
ytmagic-1.3.4.dist-info/METADATA
ytmagic-1.3.4.dist-info/WHEEL
ytmagic-1.3.4.dist-info/entry_points.txt
ytmagic-1.3.4.dist-info/top_level.txt
ytmagic-1.3.4.dist-info/RECORD
