Metadata-Version: 2.4
Name: ytmagic
Version: 1.3.4
Summary: Download videos or extract audio from YouTube, Instagram, Facebook, TikTok, X (Twitter), and more — easily and fast.
Author-email: Meowahaha <owais786549@gmail.com>
License: MIT
Requires-Python: >=3.7
License-File: LICENSE
Requires-Dist: yt-dlp>=2024.12.30
Requires-Dist: rich
Dynamic: license-file
